setup.py
ga/__init__.py
ga/algorithms.py
ga/chromosomes.py
ga/genes.py
ga/translators.py
ga/util.py
ga.egg-info/PKG-INFO
ga.egg-info/SOURCES.txt
ga.egg-info/dependency_links.txt
ga.egg-info/top_level.txt
ga/examples/__init__.py
ga/examples/__main__.py
ga/examples/biggest_multiple.py
ga/examples/irrigation.py
ga/examples/polynomials.py
ga/examples/travelling_salesman.py