Metadata-Version: 1.0
Name: ga
Version: 0.1.1.dev
Summary: A lightweight genetic algorithm library written in pure Python
Home-page: https://github.com/mdscruggs/ga
Author: Matt Scruggs
Author-email: UNKNOWN
License: GNU GPLv3
Platform: UNKNOWN
